typed_cache/__init__.py
typed_cache/_cache.py
typed_cache/_compatibility.py
typed_cache-0.2.5.dist-info/LICENSE
typed_cache-0.2.5.dist-info/METADATA
typed_cache-0.2.5.dist-info/WHEEL
typed_cache-0.2.5.dist-info/RECORD
