Metadata-Version: 2.1
Name: typed-cache
Version: 0.2.5
Summary: A framework for caching data locally. It features explicit caching with priority support for type hints.
License: MIT
Author: panhaoyu
Author-email: panhaoyu.china@outlook.com
Requires-Python: >=3.6,<4.0
Classifier: License :: OSI Approved :: MIT License
Classifier: Programming Language :: Python :: 3
Classifier: Programming Language :: Python :: 3.6
Classifier: Programming Language :: Python :: 3.7
Classifier: Programming Language :: Python :: 3.8
Classifier: Programming Language :: Python :: 3.9
Classifier: Programming Language :: Python :: 3.10
Classifier: Programming Language :: Python :: 3.11
Classifier: Programming Language :: Python :: 3.12
Requires-Dist: dataclasses (>=0.8,<0.9) ; python_version < "3.7"
